{
  "config": {
    "step": {
      "user": {
        "title": "Admin-Benutzer zum Umschalten auswählen",
        "description": "Wählen Sie den Administrator-Account aus, für den ein Schalter erstellt werden soll.",
        "data": {
          "user_id": "Admin-Benutzer"
        }
      }
    },
    "error": {
      "unknown": "Ein unbekannter Fehler ist aufgetreten.",
      "cannot_connect": "Verbindung fehlgeschlagen."
    },
    "abort": {
      "no_admin_users": "Es wurden keine anderen Administrator-Benutzer zum Konfigurieren gefunden.",
      "already_configured": "Dieser Benutzer ist bereits konfiguriert."
    }
  }
}